{
    "name": "臺北府城東門",
    "area": "TPE",
    "level": "國定古蹟",
    "address": "臺北市中正區中山南路與凱達格蘭大道交叉口圓環",
    "traffic": [
        [
            "捷運",
            "➔ 捷運臺大醫院站二號出口，沿常德街直行至中山南路右轉，在直行至凱達格蘭大道，步行約5分鐘即達。<br />"
        ],
        [
            "公車",
            "➔ 公車245、263、270、621、630、651仁愛中山路。<br />"
        ]
    ],
    "ticket": "免費參觀",
    "openingHours": "全天開放",
    "source": [
        "https://zh.wikipedia.org/wiki/%E8%87%BA%E5%8C%97%E5%BA%9C%E5%9F%8E%E6%9D%B1%E9%96%80",
        "https://nchdb.boch.gov.tw/assets/overview/monument/19980903000001"
    ],
    "img": [
        570,
        571
    ],
    "article": [
        [
            "簡介",
            "臺北府城東門，正式名稱為景福門，是位於臺灣臺北市中正區的清代城門建築，建於光緒8年（1882年）。<br />"
        ],
        [
            "歷史沿革",
            "景福門即東門，位於東城牆中央略偏南處，朝向台灣北部的重要口岸---基隆，負有防禦的重任。另外，它也是台北城通錫口（今松山）的孔道。當時城內通往東門的「東門街」，就是今天的凱達格蘭大道。臺北府城東門是現存的台北府城城門中環境最為寬廣的。現今列為中華民國國定古蹟之一。<br />昔日是臺北府城通往錫口（今松山）等臺北東郊聚落的主要孔道，今日因處於總統府、凱達格蘭大道、中正紀念堂等臺北重要地標之間，在臺北府城四大城門中與北門（承恩門）同富盛名。又因面臨東方，在日治時期時別名為照正門。<br />光復後，政府整修舊城門，東門從碉堡型的城門，被重修成宮殿式建築，大失原貌，但石構臺座及圓拱門為原有建材，門洞為石條所砌半圓拱，邊框保存有雷紋裝飾，仍頗具歷史價值。<br />1966年，臺北市政府以「整頓市容以符合觀光需要」為由，將該城門的華南式樓閣與大部分的城墩拆除，改建為仿華北式建築，此後盡失清代原貌。<br />"
        ],
        [
            "建築特色",
            "東門為台北府城五城門中石作最為精緻的，額題景福門，建築結構和北門很類似，都是在石砌的城座以上，有厚實的磚牆一直接到屋簷下，宛如牢不可破的方形堡壘。而雙層磚牆之內，則是木造結構。屋頂是四面屋坡的「歇山式」，簡單大方。和北門不同的是，東門屋簷下有綠釉空心花磚裝飾，而且兩側門孔旁均加開方形窗洞。另外，北門的外廓是方形，東門則是圓弧形。<br />城樓的臺座由石條砌成，額題「景福門」，二樓採【回】字型雙層牆壁，內室有4根大柱支撐屋頂、屋頂現為歇山單簷式，但城樓簷下多了一條裝飾帶，左右城牆上多出方窗設計。<br />"
        ]
    ]
}