{
    "name": "烏鬼井",
    "area": "TNN",
    "level": "直轄市定古蹟",
    "address": "台南市北區自強街146巷10號",
    "traffic": [
        [
            "大眾運輸",
            "➔ 搭乘火車站至台南火車站下車，走到火車站南站搭乘11號公車，至公園南路下車，約步行3分鐘即可抵達。<br />"
        ],
        [
            "開車",
            "➔ 走國道一號下新市交流道→走台一線往市區方向→接西門路→再接成功路直走→接自強街→烏鬼井<br />"
        ]
    ],
    "ticket": "免費參觀",
    "openingHours": "全天開放",
    "source": [
        "https://zh.wikipedia.org/wiki/%E7%83%8F%E9%AC%BC%E4%BA%95",
        "https://nchdb.boch.gov.tw/assets/overview/monument/19851127000066"
    ],
    "img": [
        307,
        308
    ],
    "article": [
        [
            "簡介",
            "烏鬼井位於臺南市北區，於民國七十四年（1985年）11月27日公告為三級古蹟。據說是荷蘭東印度公司命令印尼班達島土人所蓋，而因為班達島土人膚色黝黑又頗識水性，遂被稱作「烏鬼」，井名也因此而來。<br />"
        ],
        [
            "歷史沿革",
            "烏鬼井位於臺灣府城鎮北坊水仔尾北邊，約在1653年時為荷蘭東印度公司所鑿。因砌以林投，所以又名林投井。其水源豐沛，常為往來商船所用。到了乾隆時期，該井改砌磚壁，直徑為1.85公尺，深3.48公尺，而水位常保在地下57公分處。到了日治時期，該井一度被填土掩埋，直到民國四十四年（1955年）才由臺南市文獻委員會勘考挖掘並修復，供附近居民使用。然而隨著自來水的普及，該井便不再使用，並且為了安全因素而加上水泥蓋。<br />"
        ],
        [
            "特色",
            "臺灣所稱的烏鬼，由乾隆十七年(西元一七五二年)王必昌編輯的《重修臺灣縣志》中提到：「烏鬼，番國名，紅毛奴也，其人遍體純黑。」，紅毛指的是荷蘭人，那麼烏鬼便是荷蘭人帶來的混身黑皮膚的奴才了。連雅堂在《臺南古蹟志》裡提到，烏鬼其實就是黑奴，非洲地區的人，通常被用來開闢荒地或當奴隸使用，身份非常低賤，幹活做事如同牛、馬般的勞碌。所以，烏鬼井的書意可說是烏鬼開鑿的井或烏鬼使用的井。根據王必昌《重修臺灣縣志》雜記志的古蹟編說到:「紅毛命烏鬼鑿井」，因此，臺南烏鬼井即是荷蘭人命黑奴們所開鑿而做為飲用的井。<br />烏鬼井原是以箖荼(林投)來砌築，也稱箖荼井。乾隆年間改用磚砌井壁，日治時期，曾被填塞，民國四十四年十月，市政府重新挖掘修葺。現今自來水供應乾淨便利，烏鬼井雖仍有水源而且井水清澈，但鄰近居民已少飲用。<br />"
        ]
    ]
}